multibar/__init__.py
multibar/api/__init__.py
multibar/api/calculation_service.py
multibar/api/clients.py
multibar/api/contracts.py
multibar/api/hooks.py
multibar/api/progressbars.py
multibar/api/sectors.py
multibar/api/signatures.py
multibar/api/writers.py
multibar/errors.py
multibar/impl/__init__.py
multibar/impl/calculation_service.py
multibar/impl/clients.py
multibar/impl/contracts.py
multibar/impl/hooks.py
multibar/impl/progressbars.py
multibar/impl/sectors.py
multibar/impl/signatures.py
multibar/impl/writers.py
multibar/output.py
multibar/py.typed
multibar/settings.py
multibar/types.py
multibar/utils.py
python_multibar-4.0.2.dist-info/LICENSE.md
python_multibar-4.0.2.dist-info/WHEEL
python_multibar-4.0.2.dist-info/METADATA
python_multibar-4.0.2.dist-info/RECORD
