Metadata-Version: 2.1
Name: python-multibar
Version: 4.0.2
Summary: Flexible wrapper for static progressbar writing.
Home-page: https://github.com/Animatea/python-multibar
License: Apache-2.0
Keywords: progressbar,progress,multibar,python-multibar,python,python3,progress bar,utility
Author: DenyS
Author-email: animatea.programming@gmail.com
Requires-Python: >=3.9,<4.0
Classifier: Intended Audience :: Developers
Classifier: License :: OSI Approved :: Apache Software License
Classifier: Natural Language :: English
Classifier: Operating System :: OS Independent
Classifier: Programming Language :: Python :: 3
Classifier: Programming Language :: Python :: 3.9
Classifier: Programming Language :: Python :: 3.10
Classifier: Programming Language :: Python :: 3.10
Classifier: Programming Language :: Python :: 3.9
Classifier: Programming Language :: Python :: Implementation :: CPython
Classifier: Topic :: Software Development :: Libraries
Classifier: Topic :: Software Development :: Libraries :: Python Modules
Classifier: Topic :: Utilities
Classifier: Typing :: Typed
Requires-Dist: returns (==0.19.0)
Requires-Dist: termcolor (==2.0.0)
Project-URL: Bug Tracker, https://github.com/Animatea/python-multibar/issues
Project-URL: Documentation, https://animatea.github.io/python-multibar/
Project-URL: Repository, https://github.com/Animatea/python-multibar
